{
  "name": "霍华德",
  "occupation": "神秘学家",
  "age": 34,
  "era": "1920年代",
  "created_at": "2026-06-23T23:00:34.387559",
  "attributes": {
    "STR": 80,
    "DEX": 75,
    "CON": 40,
    "INT": 75,
    "POW": 60,
    "SIZ": 85,
    "APP": 80,
    "EDU": 60
  },
  "derived": {
    "HP": 12,
    "max_HP": 12,
    "SAN": 60,
    "max_SAN": 60,
    "MP": 12,
    "MOV": 8,
    "DB": "+1D6",
    "BUILD": 2,
    "LUCK": 35
  },
  "skills": {
    "dodge": 37,
    "language_own": 60,
    "fighting_brawl": 25,
    "firearms_handgun": 20,
    "firearms_rifle": 25,
    "spot_hidden": 38,
    "listen": 20,
    "stealth": 20,
    "library_use": 47,
    "first_aid": 30,
    "psychology": 54,
    "persuade": 10,
    "charm": 15,
    "fast_talk": 5,
    "intimidate": 25,
    "climb": 20,
    "jump": 20,
    "swim": 20,
    "throw": 20,
    "occult": 42,
    "history": 27,
    "law": 5,
    "locksmith": 1,
    "navigate": 10,
    "drive_auto": 20,
    "ride": 5,
    "appraise": 20,
    "archaeology": 28,
    "anthropology": 26,
    "disguise": 5,
    "science": 1,
    "medicine": 1,
    "natural_world": 10,
    "track": 30,
    "survival": 10,
    "psychoanalysis": 1,
    "sleight_of_hand": 10,
    "mech_repair": 10,
    "elec_repair": 10,
    "op_hv_machine": 18,
    "accounting": 5,
    "pilot": 1,
    "arts_craft": 5,
    "language_latin": 1,
    "credit_rating": 27,
    "cthulhu_mythos": 0
  },
  "credit_rating": 27,
  "inventory": [
    "泛黄的仪式书",
    "银质符咒",
    "蜡烛",
    "笔记本与炭笔"
  ],
  "backstory": {
    "description": "受过良好教育的神秘学研究者，对禁忌文本有危险的好奇心。",
    "beliefs": "真正的历史总藏在被删去的脚注里。",
    "important_person": "",
    "meaningful_place": "",
    "treasured_possession": "泛黄的仪式书",
    "traits": "学识渊博、好奇心强、对超自然现象缺乏应有的退缩本能。",
    "key_connection": ""
  },
  "psychological_profile": {
    "traits": [],
    "key_relationships": [],
    "phobias": [],
    "manias": []
  },
  "career": {
    "reputation": 0,
    "titles": [],
    "known_contacts": [],
    "completed_modules": [],
    "case_history": []
  }
}
